projetly_dev_tools/__init__.py
projetly_dev_tools/cli.py
projetly_dev_tools/projetly_dev_tools.py
projetly_dev_tools/plugin_template/__init__.py
projetly_dev_tools/plugin_template/plugin_handler.py
projetly_dev_tools/plugin_template/plugin/.env.template
projetly_dev_tools/plugin_template/plugin/__init__.py
projetly_dev_tools/plugin_template/plugin/api_handler.py.template
projetly_dev_tools/plugin_template/plugin/auth_handler.py.template
projetly_dev_tools/plugin_template/plugin/config.py.template
projetly_dev_tools/plugin_template/plugin/events_handler.py.template
projetly_dev_tools/plugin_template/plugin/hookresolver.py.template
projetly_dev_tools/plugin_template/plugin/request_handler.py.template
projetly_dev_tools/plugin_template/plugin/utils.py.template
projetly_dev_tools/plugin_template/plugin/auth/__init__.py
projetly_dev_tools/plugin_template/plugin/auth/decorators.py.template
projetly_dev_tools/plugin_template/plugin/auth/jwt.py.template
projetly_dev_tools/plugin_template/plugin/parser/__init__.py
projetly_dev_tools-0.0.1.dist-info/METADATA
projetly_dev_tools-0.0.1.dist-info/WHEEL
projetly_dev_tools-0.0.1.dist-info/entry_points.txt
projetly_dev_tools-0.0.1.dist-info/top_level.txt
projetly_dev_tools-0.0.1.dist-info/RECORD
