Metadata-Version: 2.1
Name: projetly-dev-tools
Version: 0.0.1
Summary: Projetly dev tool for plugins management.
Author: Roopesh Kumar
Author-email: roopesh@projetly.ai
Classifier: Programming Language :: Python :: 3
Classifier: License :: OSI Approved :: MIT License
Classifier: Operating System :: OS Independent
Requires-Python: >=3.11
